lightcon/__config__.py
lightcon/__init__.py
lightcon/_globals.py
lightcon/beam_alignment/__init__.py
lightcon/beam_alignment/_beam_alignment.py
lightcon/calculate/__init__.py
lightcon/calculate/_calculate_motor_parameters.py
lightcon/camera_app_client/__init__.py
lightcon/camera_app_client/_camera_app_client.py
lightcon/common/__init__.py
lightcon/common/_converters.py
lightcon/common/_http_methods.py
lightcon/common/_leprecan_provider.py
lightcon/common/_load_motor_and_stage_parameters.py
lightcon/common/_logging.py
lightcon/common/_serial_tools.py
lightcon/common/_udp_locator.py
lightcon/cronus2p/__init__.py
lightcon/cronus2p/_c2pcontrol.py
lightcon/cronus3p/__init__.py
lightcon/cronus3p/_c3pcontrol.py
lightcon/datasets/__init__.py
lightcon/datasets/_base.py
lightcon/datasets/data/__init__.py
lightcon/datasets/data/motor_parameters.json
lightcon/datasets/data/stage_parameters.json
lightcon/eth_motor_board/__init__.py
lightcon/eth_motor_board/_eth_motor_board.py
lightcon/eth_motor_board/_eth_motor_board_leprecan_provider.py
lightcon/fast_daq/FTD2XX_NET.dll
lightcon/fast_daq/LightConversion.Abstractions.dll
lightcon/fast_daq/LightConversion.Hardware.FastDaq.dll
lightcon/fast_daq/System.Threading.dll
lightcon/fast_daq/__init__.py
lightcon/fast_daq/_fast_daq.py
lightcon/harpia/__init__.py
lightcon/harpia/_harpia.py
lightcon/harpia/_harpia_leprecan_provider.py
lightcon/harpia/_harpia_model_decoder.py
lightcon/harpia_daq/FTD2XX_NET.dll
lightcon/harpia_daq/FTD2XX_NET.xml
lightcon/harpia_daq/LightConversion.Abstractions.dll
lightcon/harpia_daq/LightConversion.Hardware.HarpiaDaq.dll
lightcon/harpia_daq/LightConversion.Hardware.HarpiaDaq.xml
lightcon/harpia_daq/System.Threading.dll
lightcon/harpia_daq/__init__.py
lightcon/harpia_daq/_harpia_daq.py
lightcon/laser_clients/__init__.py
lightcon/laser_clients/_laser_clients.py
lightcon/power_meter/__init__.py
lightcon/power_meter/_power_meter.py
lightcon/spectrometers/__init__.py
lightcon/spectrometers/_remote_spectrometer.py
lightcon-1.5.15.dist-info/LICENCE
lightcon-1.5.15.dist-info/METADATA
lightcon-1.5.15.dist-info/WHEEL
lightcon-1.5.15.dist-info/top_level.txt
lightcon-1.5.15.dist-info/RECORD
