Metadata-Version: 2.1
Name: lightcon
Version: 1.5.15
Summary: A set of APIs to Light Conversion devices
Home-page: https://bitbucket.org/harpiasoftware/light-conversion-apis.git
Author: Vytautas Butkus
Author-email: vytautas.butkus@lightcon.com
Project-URL: Documentation, https://lightconupdater.blob.core.windows.net/documentation/lightcon/index.html
Classifier: Programming Language :: Python :: 3
Classifier: License :: OSI Approved :: MIT License
Classifier: Operating System :: OS Independent
Classifier: Development Status :: 1 - Planning
Requires-Python: >=3.7
License-File: LICENCE
Requires-Dist: pythonnet>=3.0.0
Requires-Dist: pyserial
Requires-Dist: numpy
Requires-Dist: typing-extensions
Requires-Dist: requests
Requires-Dist: pytest
